aliyunsdkjarvis/__init__.py
aliyunsdkjarvis/request/__init__.py
aliyunsdkjarvis/request/v20180206/CreateAccessWhiteListGroupRequest.py
aliyunsdkjarvis/request/v20180206/CreateAllEcsWhiteListRequest.py
aliyunsdkjarvis/request/v20180206/CreateCdnIpRequest.py
aliyunsdkjarvis/request/v20180206/CreateCdnSubscriptionRequest.py
aliyunsdkjarvis/request/v20180206/CreateConsoleAccessWhiteListRequest.py
aliyunsdkjarvis/request/v20180206/CreateCpmcPunishFeedBackRequest.py
aliyunsdkjarvis/request/v20180206/CreateIpWhiteBaselineRequest.py
aliyunsdkjarvis/request/v20180206/CreateMiningApplyRequest.py
aliyunsdkjarvis/request/v20180206/CreateMiningReportRequest.py
aliyunsdkjarvis/request/v20180206/CreateMiningRevokeRequest.py
aliyunsdkjarvis/request/v20180206/CreateUidWhiteBaselineRequest.py
aliyunsdkjarvis/request/v20180206/CreateUidWhiteListGroupRequest.py
aliyunsdkjarvis/request/v20180206/DeleteAccessWhiteListGroupRequest.py
aliyunsdkjarvis/request/v20180206/DeleteCdnIpRequest.py
aliyunsdkjarvis/request/v20180206/DeleteCdnSubscriptionRequest.py
aliyunsdkjarvis/request/v20180206/DeleteConsoleAccessWhiteListRequest.py
aliyunsdkjarvis/request/v20180206/DeleteCpmcPunishRequest.py
aliyunsdkjarvis/request/v20180206/DeleteIpWhiteBaselineRequest.py
aliyunsdkjarvis/request/v20180206/DeleteUidWhiteBaselineRequest.py
aliyunsdkjarvis/request/v20180206/DeleteUidWhiteListGroupRequest.py
aliyunsdkjarvis/request/v20180206/DeleteWhiteListConditionalRequest.py
aliyunsdkjarvis/request/v20180206/DeleteWhiteListDbItemConditionalRequest.py
aliyunsdkjarvis/request/v20180206/DescribeAccessWhiteListEipListRequest.py
aliyunsdkjarvis/request/v20180206/DescribeAccessWhiteListGroupRequest.py
aliyunsdkjarvis/request/v20180206/DescribeAccessWhiteListRdsListRequest.py
aliyunsdkjarvis/request/v20180206/DescribeAccessWhiteListSlbListRequest.py
aliyunsdkjarvis/request/v20180206/DescribeAccessWhiteListSwasListRequest.py
aliyunsdkjarvis/request/v20180206/DescribeAccessWhitelistEcsListRequest.py
aliyun_python_sdk_jarvis-1.0.0.dist-info/LICENSE
aliyun_python_sdk_jarvis-1.0.0.dist-info/METADATA
aliyun_python_sdk_jarvis-1.0.0.dist-info/WHEEL
aliyun_python_sdk_jarvis-1.0.0.dist-info/top_level.txt
aliyun_python_sdk_jarvis-1.0.0.dist-info/RECORD
